xchainpy2_base/__init__.py
xchainpy2_base/base_client.py
xchainpy2_base/const.py
xchainpy2_base/data/base_mainnet_latest.json
xchainpy2_base-0.0.4.dist-info/LICENSE
xchainpy2_base-0.0.4.dist-info/METADATA
xchainpy2_base-0.0.4.dist-info/WHEEL
xchainpy2_base-0.0.4.dist-info/top_level.txt
xchainpy2_base-0.0.4.dist-info/RECORD
